vnpy_sopt-3.7.1.1.dist-info/METADATA
vnpy_sopt-3.7.1.1.dist-info/WHEEL
vnpy_sopt/api/vnsoptmd.cp313-win_amd64.pyd
vnpy_sopt/api/vnsoptmd.cp313-win_amd64.lib
vnpy_sopt/api/vnsopttd.cp313-win_amd64.pyd
vnpy_sopt/api/vnsopttd.cp313-win_amd64.lib
vnpy_sopt/__init__.py
vnpy_sopt/api/__init__.py
vnpy_sopt/api/sopt_constant.py
vnpy_sopt/gateway/__init__.py
vnpy_sopt/gateway/sopt_gateway.py
vnpy_sopt/api/soptthostmduserapi_se.dll
vnpy_sopt/api/soptthosttraderapi_se.dll
vnpy_sopt-3.7.1.1.dist-info/RECORD
